MANIFEST.in
setup.py
mapfish/__init__.py
mapfish/commands.py
mapfish/protocol.py
mapfish/sqlalchemygeom.py
mapfish/util.py
mapfish.egg-info/PKG-INFO
mapfish.egg-info/SOURCES.txt
mapfish.egg-info/dependency_links.txt
mapfish.egg-info/entry_points.txt
mapfish.egg-info/not-zip-safe
mapfish.egg-info/requires.txt
mapfish.egg-info/top_level.txt
mapfish/controllers/__init__.py
mapfish/controllers/auth_proxy.py
mapfish/controllers/printer.py
mapfish/controllers/security.py
mapfish/decorators/__init__.py
mapfish/plugins/__init__.py
mapfish/plugins/pgrouting.py
mapfish/templates/.controller.py_tmpl.un~
mapfish/templates/.model.py_tmpl.un~
mapfish/templates/.test_controller.py_tmpl.un~
mapfish/templates/controller.py_tmpl
mapfish/templates/model.py_tmpl
mapfish/templates/test_controller.py_tmpl
mapfish/templates/project/.layers.ini_tmpl.un~
mapfish/templates/project/layers.ini_tmpl
mapfish/tests/__init__.py
mapfish/tests/test_decorators.py
mapfish/tests/test_mysql.py
mapfish/tests/test_oracle.py
mapfish/tests/test_postgis.py
mapfish/tests/test_protocol.py
mapfish/tests/test_spatialite.py