Metadata-Version: 1.0
Name: mapfish
Version: 2.2
Summary: The MapFish web-mapping framework.
Home-page: http://www.mapfish.org
Author: Camptocamp
Author-email: UNKNOWN
License: Modified BSD
Keywords: pylons wsgi framework sqlalchemy geojson shapely GIS
Platform: UNKNOWN
Classifier: Development Status :: 4 - Beta
Classifier: Intended Audience :: Developers
Classifier: Intended Audience :: Science/Research
Classifier: License :: OSI Approved :: BSD License
Classifier: Operating System :: OS Independent
Classifier: Programming Language :: Python
Classifier: Framework :: Pylons
Classifier: Topic :: Scientific/Engineering :: GIS
Classifier: Topic :: Internet :: WWW/HTTP
Classifier: Topic :: Internet :: WWW/HTTP :: Dynamic Content
Classifier: Topic :: Internet :: WWW/HTTP :: WSGI
Classifier: Topic :: Software Development :: Libraries :: Python Modules
